azure_iot_edge_dev_tool-0.77.0.dist-info/DESCRIPTION.rst
azure_iot_edge_dev_tool-0.77.0.dist-info/METADATA
azure_iot_edge_dev_tool-0.77.0.dist-info/RECORD
azure_iot_edge_dev_tool-0.77.0.dist-info/WHEEL
azure_iot_edge_dev_tool-0.77.0.dist-info/entry_points.txt
azure_iot_edge_dev_tool-0.77.0.dist-info/metadata.json
azure_iot_edge_dev_tool-0.77.0.dist-info/top_level.txt
iotedgedev/__init__.py
iotedgedev/args.py
iotedgedev/azurecli.py
iotedgedev/cli.py
iotedgedev/connectionstring.py
iotedgedev/dockercls.py
iotedgedev/dotnetmoduleprocessor.py
iotedgedev/envvars.py
iotedgedev/iothub.py
iotedgedev/module.py
iotedgedev/modules.py
iotedgedev/modulesprocessorfactory.py
iotedgedev/moduletype.py
iotedgedev/monitor.js
iotedgedev/othermoduleprocessor.py
iotedgedev/output.py
iotedgedev/runtime.py
iotedgedev/solution.py
iotedgedev/utility.py
iotedgedev/template/template.zip
