Metadata-Version: 2.0
Name: azure-iot-edge-dev-tool
Version: 0.77.0
Summary: The Azure IoT Edge Dev Tool package greatly simplifies your IoT Edge development process by automating many of your routine manual tasks, such as building, deploying, pushing modules and configuring your IoT Edge Runtime.
Home-page: https://github.com/jonbgallant/azure-iot-edge-dev-tool
Author: Jon Gallant
Author-email: info@jongallant.com
License: MIT license
Keywords: azure iot edge dev tool
Platform: UNKNOWN
Classifier: Development Status :: 2 - Pre-Alpha
Classifier: Intended Audience :: Developers
Classifier: License :: OSI Approved :: MIT License
Classifier: Natural Language :: English
Classifier: Programming Language :: Python :: 2
Classifier: Programming Language :: Python :: 2.6
Classifier: Programming Language :: Python :: 2.7
Classifier: Programming Language :: Python :: 3
Classifier: Programming Language :: Python :: 3.3
Classifier: Programming Language :: Python :: 3.4
Classifier: Programming Language :: Python :: 3.5
Requires-Dist: Click (>=6.0)
Requires-Dist: azure-cli-cloud
Requires-Dist: azure-cli-configure
Requires-Dist: azure-cli-extension
Requires-Dist: azure-cli-iot
Requires-Dist: azure-cli-profile
Requires-Dist: azure-cli-resource
Requires-Dist: azure-iot-edge-runtime-ctl (==1.0.0rc21)
Requires-Dist: docker (==3.0.0)
Requires-Dist: fstrings
Requires-Dist: python-dotenv
Requires-Dist: requests
